MANIFEST.in
README.md
setup.py
opclabs_quickopc/__init__.py
opclabs_quickopc.egg-info/PKG-INFO
opclabs_quickopc.egg-info/SOURCES.txt
opclabs_quickopc.egg-info/dependency_links.txt
opclabs_quickopc.egg-info/not-zip-safe
opclabs_quickopc.egg-info/requires.txt
opclabs_quickopc.egg-info/top_level.txt
opclabs_quickopc/OpcLabs.QuickOpc/BouncyCastle.Cryptography_2.5.0.html
opclabs_quickopc/OpcLabs.QuickOpc/EULA-ConnectivityStudio.htm
opclabs_quickopc/OpcLabs.QuickOpc/JetBrains.Annotations_2024.3.0.html
opclabs_quickopc/OpcLabs.QuickOpc/Microsoft.AspNetCore.Connections.Abstractions_2.3.0.txt
opclabs_quickopc/OpcLabs.QuickOpc/Microsoft.AspNetCore.Hosting.Abstractions_2.3.0.txt
opclabs_quickopc/OpcLabs.QuickOpc/Microsoft.AspNetCore.Hosting.Server.Abstractions_2.3.0.txt
opclabs_quickopc/OpcLabs.QuickOpc/Microsoft.AspNetCore.Hosting_2.3.0.txt
opclabs_quickopc/OpcLabs.QuickOpc/Microsoft.AspNetCore.Http.Abstractions_2.3.0.txt
opclabs_quickopc/OpcLabs.QuickOpc/Microsoft.AspNetCore.Http.Extensions_2.3.0.txt
opclabs_quickopc/OpcLabs.QuickOpc/Microsoft.AspNetCore.Http.Features_2.3.0.txt
opclabs_quickopc/OpcLabs.QuickOpc/Microsoft.AspNetCore.Http_2.3.0.txt
opclabs_quickopc/OpcLabs.QuickOpc/Microsoft.AspNetCore.Mvc.Abstractions_2.3.0.txt
opclabs_quickopc/OpcLabs.QuickOpc/Microsoft.AspNetCore.Routing.Abstractions_2.3.0.txt
opclabs_quickopc/OpcLabs.QuickOpc/Microsoft.AspNetCore.Server.Kestrel.Core_2.3.0.txt
opclabs_quickopc/OpcLabs.QuickOpc/Microsoft.AspNetCore.Server.Kestrel.Core_2.3.6.txt
opclabs_quickopc/OpcLabs.QuickOpc/Microsoft.AspNetCore.Server.Kestrel.Https_2.3.0.txt
opclabs_quickopc/OpcLabs.QuickOpc/Microsoft.AspNetCore.Server.Kestrel.Transport.Abstractions_2.3.0.txt
opclabs_quickopc/OpcLabs.QuickOpc/Microsoft.AspNetCore.Server.Kestrel.Transport.Sockets_2.3.0.txt
opclabs_quickopc/OpcLabs.QuickOpc/Microsoft.AspNetCore.Server.Kestrel_2.3.0.txt
opclabs_quickopc/OpcLabs.QuickOpc/Microsoft.AspNetCore.WebUtilities_2.3.0.txt
opclabs_quickopc/OpcLabs.QuickOpc/Microsoft.Bcl.AsyncInterfaces_8.0.0.html
opclabs_quickopc/OpcLabs.QuickOpc/Microsoft.Bcl.AsyncInterfaces_9.0.3.html
opclabs_quickopc/OpcLabs.QuickOpc/Microsoft.Bcl.HashCode_6.0.0.html
opclabs_quickopc/OpcLabs.QuickOpc/Microsoft.CSharp_4.3.0.txt
