Metadata-Version: 2.4
Name: opclabs_quickopc
Version: 5.83.1043
Summary: QuickOPC Client and Subscriber Toolkit for OPC UA and OPC Classic.
Home-page: https://www.opclabs.com/products/quickopc/languages-and-tools/python
Author: CODE Consulting and Development, s.r.o.
Author-email: sales09@opclabs.com
Keywords: OPC,OPC-UA
License-File: opclabs_quickopc/OpcLabs.QuickOpc/EULA-ConnectivityStudio.htm
License-File: opclabs_quickopc/OpcLabs.QuickOpc/BouncyCastle.Cryptography_2.5.0.html
License-File: opclabs_quickopc/OpcLabs.QuickOpc/JetBrains.Annotations_2024.3.0.html
License-File: opclabs_quickopc/OpcLabs.QuickOpc/Microsoft.Bcl.AsyncInterfaces_8.0.0.html
License-File: opclabs_quickopc/OpcLabs.QuickOpc/Microsoft.Bcl.AsyncInterfaces_9.0.3.html
License-File: opclabs_quickopc/OpcLabs.QuickOpc/Microsoft.Bcl.HashCode_6.0.0.html
License-File: opclabs_quickopc/OpcLabs.QuickOpc/Microsoft.CSharp_4.7.0.html
License-File: opclabs_quickopc/OpcLabs.QuickOpc/Microsoft.Extensions.Caching.Abstractions_9.0.3.html
License-File: opclabs_quickopc/OpcLabs.QuickOpc/Microsoft.Extensions.Caching.Memory_9.0.3.html
License-File: opclabs_quickopc/OpcLabs.QuickOpc/Microsoft.Extensions.Configuration.Abstractions_8.0.0.html
License-File: opclabs_quickopc/OpcLabs.QuickOpc/Microsoft.Extensions.Configuration.Abstractions_9.0.3.html
License-File: opclabs_quickopc/OpcLabs.QuickOpc/Microsoft.Extensions.Configuration.Binder_8.0.2.html
License-File: opclabs_quickopc/OpcLabs.QuickOpc/Microsoft.Extensions.Configuration.Binder_9.0.3.html
License-File: opclabs_quickopc/OpcLabs.QuickOpc/Microsoft.Extensions.Configuration.CommandLine_9.0.3.html
License-File: opclabs_quickopc/OpcLabs.QuickOpc/Microsoft.Extensions.Configuration.EnvironmentVariables_8.0.0.html
License-File: opclabs_quickopc/OpcLabs.QuickOpc/Microsoft.Extensions.Configuration.EnvironmentVariables_9.0.3.html
License-File: opclabs_quickopc/OpcLabs.QuickOpc/Microsoft.Extensions.Configuration.FileExtensions_8.0.1.html
License-File: opclabs_quickopc/OpcLabs.QuickOpc/Microsoft.Extensions.Configuration.FileExtensions_9.0.3.html
License-File: opclabs_quickopc/OpcLabs.QuickOpc/Microsoft.Extensions.Configuration.Json_9.0.3.html
License-File: opclabs_quickopc/OpcLabs.QuickOpc/Microsoft.Extensions.Configuration.UserSecrets_9.0.3.html
License-File: opclabs_quickopc/OpcLabs.QuickOpc/Microsoft.Extensions.Configuration_8.0.0.html
License-File: opclabs_quickopc/OpcLabs.QuickOpc/Microsoft.Extensions.Configuration_9.0.3.html
License-File: opclabs_quickopc/OpcLabs.QuickOpc/Microsoft.Extensions.DependencyInjection.Abstractions_8.0.0.html
License-File: opclabs_quickopc/OpcLabs.QuickOpc/Microsoft.Extensions.DependencyInjection.Abstractions_8.0.2.html
License-File: opclabs_quickopc/OpcLabs.QuickOpc/Microsoft.Extensions.DependencyInjection.Abstractions_9.0.1.html
License-File: opclabs_quickopc/OpcLabs.QuickOpc/Microsoft.Extensions.DependencyInjection.Abstractions_9.0.3.html
License-File: opclabs_quickopc/OpcLabs.QuickOpc/Microsoft.Extensions.DependencyInjection_8.0.1.html
License-File: opclabs_quickopc/OpcLabs.QuickOpc/Microsoft.Extensions.DependencyInjection_9.0.3.html
License-File: opclabs_quickopc/OpcLabs.QuickOpc/Microsoft.Extensions.Diagnostics.Abstractions_8.0.1.html
License-File: opclabs_quickopc/OpcLabs.QuickOpc/Microsoft.Extensions.Diagnostics.Abstractions_9.0.3.html
License-File: opclabs_quickopc/OpcLabs.QuickOpc/Microsoft.Extensions.Diagnostics_9.0.3.html
License-File: opclabs_quickopc/OpcLabs.QuickOpc/Microsoft.Extensions.FileProviders.Abstractions_8.0.0.html
License-File: opclabs_quickopc/OpcLabs.QuickOpc/Microsoft.Extensions.FileProviders.Abstractions_9.0.3.html
License-File: opclabs_quickopc/OpcLabs.QuickOpc/Microsoft.Extensions.FileProviders.Physical_8.0.0.html
License-File: opclabs_quickopc/OpcLabs.QuickOpc/Microsoft.Extensions.FileProviders.Physical_9.0.3.html
License-File: opclabs_quickopc/OpcLabs.QuickOpc/Microsoft.Extensions.FileSystemGlobbing_8.0.0.html
License-File: opclabs_quickopc/OpcLabs.QuickOpc/Microsoft.Extensions.FileSystemGlobbing_9.0.3.html
License-File: opclabs_quickopc/OpcLabs.QuickOpc/Microsoft.Extensions.Hosting.Abstractions_8.0.1.html
License-File: opclabs_quickopc/OpcLabs.QuickOpc/Microsoft.Extensions.Hosting.Abstractions_9.0.3.html
License-File: opclabs_quickopc/OpcLabs.QuickOpc/Microsoft.Extensions.Hosting_9.0.3.html
License-File: opclabs_quickopc/OpcLabs.QuickOpc/Microsoft.Extensions.Logging.Abstractions_3.1.32.html
License-File: opclabs_quickopc/OpcLabs.QuickOpc/Microsoft.Extensions.Logging.Abstractions_6.0.4.html
License-File: opclabs_quickopc/OpcLabs.QuickOpc/Microsoft.Extensions.Logging.Abstractions_8.0.2.html
License-File: opclabs_quickopc/OpcLabs.QuickOpc/Microsoft.Extensions.Logging.Abstractions_9.0.1.html
License-File: opclabs_quickopc/OpcLabs.QuickOpc/Microsoft.Extensions.Logging.Abstractions_9.0.3.html
License-File: opclabs_quickopc/OpcLabs.QuickOpc/Microsoft.Extensions.Logging.Configuration_9.0.3.html
License-File: opclabs_quickopc/OpcLabs.QuickOpc/Microsoft.Extensions.Logging.Console_9.0.3.html
License-File: opclabs_quickopc/OpcLabs.QuickOpc/Microsoft.Extensions.Logging.Debug_8.0.1.html
License-File: opclabs_quickopc/OpcLabs.QuickOpc/Microsoft.Extensions.Logging.Debug_9.0.3.html
License-File: opclabs_quickopc/OpcLabs.QuickOpc/Microsoft.Extensions.Logging.EventLog_9.0.3.html
License-File: opclabs_quickopc/OpcLabs.QuickOpc/Microsoft.Extensions.Logging.EventSource_9.0.3.html
License-File: opclabs_quickopc/OpcLabs.QuickOpc/Microsoft.Extensions.Logging_8.0.1.html
License-File: opclabs_quickopc/OpcLabs.QuickOpc/Microsoft.Extensions.Logging_9.0.3.html
License-File: opclabs_quickopc/OpcLabs.QuickOpc/Microsoft.Extensions.ObjectPool_8.0.11.html
License-File: opclabs_quickopc/OpcLabs.QuickOpc/Microsoft.Extensions.Options.ConfigurationExtensions_9.0.3.html
License-File: opclabs_quickopc/OpcLabs.QuickOpc/Microsoft.Extensions.Options_8.0.2.html
License-File: opclabs_quickopc/OpcLabs.QuickOpc/Microsoft.Extensions.Options_9.0.3.html
License-File: opclabs_quickopc/OpcLabs.QuickOpc/Microsoft.Extensions.Primitives_8.0.0.html
License-File: opclabs_quickopc/OpcLabs.QuickOpc/Microsoft.Extensions.Primitives_9.0.3.html
License-File: opclabs_quickopc/OpcLabs.QuickOpc/Microsoft.NETCore.Platforms_5.0.0.html
License-File: opclabs_quickopc/OpcLabs.QuickOpc/Microsoft.Win32.Registry_5.0.0.html
License-File: opclabs_quickopc/OpcLabs.QuickOpc/Microsoft.Win32.SystemEvents_6.0.0.html
License-File: opclabs_quickopc/OpcLabs.QuickOpc/Microsoft.Win32.SystemEvents_7.0.0.html
License-File: opclabs_quickopc/OpcLabs.QuickOpc/Newtonsoft.Json_13.0.3.html
License-File: opclabs_quickopc/OpcLabs.QuickOpc/OPCFoundation.NetStandard.Opc.Ua.Client_1.5.376.213.html
License-File: opclabs_quickopc/OpcLabs.QuickOpc/OPCFoundation.NetStandard.Opc.Ua.Configuration_1.5.376.213.html
License-File: opclabs_quickopc/OpcLabs.QuickOpc/OPCFoundation.NetStandard.Opc.Ua.Gds.Client.Common_1.5.376.213.html
License-File: opclabs_quickopc/OpcLabs.QuickOpc/OPCFoundation.NetStandard.Opc.Ua.Security.Certificates_1.5.376.213.html
License-File: opclabs_quickopc/OpcLabs.QuickOpc/System.Buffers_4.6.0.html
License-File: opclabs_quickopc/OpcLabs.QuickOpc/System.CodeDom_6.0.0.html
License-File: opclabs_quickopc/OpcLabs.QuickOpc/System.Collections.Immutable_8.0.0.html
License-File: opclabs_quickopc/OpcLabs.QuickOpc/System.ComponentModel.Annotations_5.0.0.html
License-File: opclabs_quickopc/OpcLabs.QuickOpc/System.Configuration.ConfigurationManager_6.0.0.html
License-File: opclabs_quickopc/OpcLabs.QuickOpc/System.Diagnostics.DiagnosticSource_6.0.2.html
License-File: opclabs_quickopc/OpcLabs.QuickOpc/System.Diagnostics.DiagnosticSource_8.0.1.html
License-File: opclabs_quickopc/OpcLabs.QuickOpc/System.Diagnostics.DiagnosticSource_9.0.3.html
License-File: opclabs_quickopc/OpcLabs.QuickOpc/System.Diagnostics.EventLog_9.0.3.html
License-File: opclabs_quickopc/OpcLabs.QuickOpc/System.Drawing.Common_6.0.0.html
License-File: opclabs_quickopc/OpcLabs.QuickOpc/System.Drawing.Common_7.0.0.html
License-File: opclabs_quickopc/OpcLabs.QuickOpc/System.Formats.Asn1_5.0.0.html
License-File: opclabs_quickopc/OpcLabs.QuickOpc/System.Formats.Asn1_6.0.0.html
License-File: opclabs_quickopc/OpcLabs.QuickOpc/System.Formats.Asn1_8.0.1.html
License-File: opclabs_quickopc/OpcLabs.QuickOpc/System.Formats.Asn1_9.0.1.html
License-File: opclabs_quickopc/OpcLabs.QuickOpc/System.IO.Pipelines_8.0.0.html
License-File: opclabs_quickopc/OpcLabs.QuickOpc/System.IO.Pipelines_9.0.3.html
License-File: opclabs_quickopc/OpcLabs.QuickOpc/System.Interactive_5.0.0.html
License-File: opclabs_quickopc/OpcLabs.QuickOpc/System.Memory_4.6.0.html
License-File: opclabs_quickopc/OpcLabs.QuickOpc/System.Numerics.Vectors_4.6.0.html
License-File: opclabs_quickopc/OpcLabs.QuickOpc/System.Private.ServiceModel_4.7.0.html
License-File: opclabs_quickopc/OpcLabs.QuickOpc/System.Reactive_5.0.0.html
License-File: opclabs_quickopc/OpcLabs.QuickOpc/System.Reflection.Metadata_8.0.1.html
License-File: opclabs_quickopc/OpcLabs.QuickOpc/System.Reflection.TypeExtensions_4.7.0.html
License-File: opclabs_quickopc/OpcLabs.QuickOpc/System.Runtime.CompilerServices.Unsafe_6.0.0.html
License-File: opclabs_quickopc/OpcLabs.QuickOpc/System.Runtime.CompilerServices.Unsafe_6.1.0.html
License-File: opclabs_quickopc/OpcLabs.QuickOpc/System.Runtime.Serialization.Formatters_9.0.3.html
License-File: opclabs_quickopc/OpcLabs.QuickOpc/System.Security.AccessControl_5.0.0.html
License-File: opclabs_quickopc/OpcLabs.QuickOpc/System.Security.AccessControl_6.0.0.html
License-File: opclabs_quickopc/OpcLabs.QuickOpc/System.Security.Cryptography.Cng_5.0.0.html
License-File: opclabs_quickopc/OpcLabs.QuickOpc/System.Security.Cryptography.Pkcs_6.0.1.html
License-File: opclabs_quickopc/OpcLabs.QuickOpc/System.Security.Cryptography.Pkcs_6.0.3.html
License-File: opclabs_quickopc/OpcLabs.QuickOpc/System.Security.Cryptography.ProtectedData_6.0.0.html
License-File: opclabs_quickopc/OpcLabs.QuickOpc/System.Security.Cryptography.Xml_6.0.1.html
License-File: opclabs_quickopc/OpcLabs.QuickOpc/System.Security.Permissions_6.0.0.html
License-File: opclabs_quickopc/OpcLabs.QuickOpc/System.Security.Principal.Windows_5.0.0.html
License-File: opclabs_quickopc/OpcLabs.QuickOpc/System.ServiceModel.Duplex_4.7.0.html
License-File: opclabs_quickopc/OpcLabs.QuickOpc/System.ServiceModel.Http_4.7.0.html
License-File: opclabs_quickopc/OpcLabs.QuickOpc/System.ServiceModel.NetTcp_4.7.0.html
License-File: opclabs_quickopc/OpcLabs.QuickOpc/System.ServiceModel.Primitives_4.7.0.html
License-File: opclabs_quickopc/OpcLabs.QuickOpc/System.ServiceModel.Security_4.7.0.html
License-File: opclabs_quickopc/OpcLabs.QuickOpc/System.Text.Encodings.Web_8.0.0.html
License-File: opclabs_quickopc/OpcLabs.QuickOpc/System.Text.Encodings.Web_9.0.3.html
License-File: opclabs_quickopc/OpcLabs.QuickOpc/System.Text.Json_9.0.3.html
License-File: opclabs_quickopc/OpcLabs.QuickOpc/System.Threading.Tasks.Extensions_4.6.0.html
License-File: opclabs_quickopc/OpcLabs.QuickOpc/System.Windows.Extensions_6.0.0.html
License-File: opclabs_quickopc/OpcLabs.QuickOpc/Microsoft.AspNetCore.Connections.Abstractions_2.3.0.txt
License-File: opclabs_quickopc/OpcLabs.QuickOpc/Microsoft.AspNetCore.Hosting.Abstractions_2.3.0.txt
License-File: opclabs_quickopc/OpcLabs.QuickOpc/Microsoft.AspNetCore.Hosting.Server.Abstractions_2.3.0.txt
License-File: opclabs_quickopc/OpcLabs.QuickOpc/Microsoft.AspNetCore.Hosting_2.3.0.txt
License-File: opclabs_quickopc/OpcLabs.QuickOpc/Microsoft.AspNetCore.Http.Abstractions_2.3.0.txt
License-File: opclabs_quickopc/OpcLabs.QuickOpc/Microsoft.AspNetCore.Http.Extensions_2.3.0.txt
License-File: opclabs_quickopc/OpcLabs.QuickOpc/Microsoft.AspNetCore.Http.Features_2.3.0.txt
License-File: opclabs_quickopc/OpcLabs.QuickOpc/Microsoft.AspNetCore.Http_2.3.0.txt
License-File: opclabs_quickopc/OpcLabs.QuickOpc/Microsoft.AspNetCore.Mvc.Abstractions_2.3.0.txt
License-File: opclabs_quickopc/OpcLabs.QuickOpc/Microsoft.AspNetCore.Routing.Abstractions_2.3.0.txt
License-File: opclabs_quickopc/OpcLabs.QuickOpc/Microsoft.AspNetCore.Server.Kestrel.Core_2.3.0.txt
License-File: opclabs_quickopc/OpcLabs.QuickOpc/Microsoft.AspNetCore.Server.Kestrel.Core_2.3.6.txt
License-File: opclabs_quickopc/OpcLabs.QuickOpc/Microsoft.AspNetCore.Server.Kestrel.Https_2.3.0.txt
License-File: opclabs_quickopc/OpcLabs.QuickOpc/Microsoft.AspNetCore.Server.Kestrel.Transport.Abstractions_2.3.0.txt
License-File: opclabs_quickopc/OpcLabs.QuickOpc/Microsoft.AspNetCore.Server.Kestrel.Transport.Sockets_2.3.0.txt
License-File: opclabs_quickopc/OpcLabs.QuickOpc/Microsoft.AspNetCore.Server.Kestrel_2.3.0.txt
License-File: opclabs_quickopc/OpcLabs.QuickOpc/Microsoft.AspNetCore.WebUtilities_2.3.0.txt
License-File: opclabs_quickopc/OpcLabs.QuickOpc/Microsoft.CSharp_4.3.0.txt
License-File: opclabs_quickopc/OpcLabs.QuickOpc/Microsoft.NETCore.Platforms_1.0.1.txt
License-File: opclabs_quickopc/OpcLabs.QuickOpc/Microsoft.NETCore.Platforms_1.1.0.txt
License-File: opclabs_quickopc/OpcLabs.QuickOpc/Microsoft.NETCore.Platforms_1.1.1.txt
License-File: opclabs_quickopc/OpcLabs.QuickOpc/Microsoft.NETCore.Platforms_2.0.0.txt
License-File: opclabs_quickopc/OpcLabs.QuickOpc/Microsoft.NETCore.Targets_1.0.1.txt
License-File: opclabs_quickopc/OpcLabs.QuickOpc/Microsoft.NETCore.Targets_1.1.0.txt
License-File: opclabs_quickopc/OpcLabs.QuickOpc/Microsoft.Net.Http.Headers_2.3.0.txt
License-File: opclabs_quickopc/OpcLabs.QuickOpc/Microsoft.Win32.Primitives_4.3.0.txt
License-File: opclabs_quickopc/OpcLabs.QuickOpc/NETStandard.Library_1.6.1.txt
License-File: opclabs_quickopc/OpcLabs.QuickOpc/OPCFoundation.NetStandard.Opc.Ua.Bindings.Https_1.5.376.213.txt
License-File: opclabs_quickopc/OpcLabs.QuickOpc/OPCFoundation.NetStandard.Opc.Ua.Core_1.5.376.213.txt
License-File: opclabs_quickopc/OpcLabs.QuickOpc/System.AppContext_4.3.0.txt
License-File: opclabs_quickopc/OpcLabs.QuickOpc/System.Buffers_4.3.0.txt
License-File: opclabs_quickopc/OpcLabs.QuickOpc/System.Buffers_4.4.0.txt
License-File: opclabs_quickopc/OpcLabs.QuickOpc/System.Buffers_4.5.1.txt
License-File: opclabs_quickopc/OpcLabs.QuickOpc/System.Collections.Concurrent_4.3.0.txt
License-File: opclabs_quickopc/OpcLabs.QuickOpc/System.Collections.NonGeneric_4.3.0.txt
License-File: opclabs_quickopc/OpcLabs.QuickOpc/System.Collections.Specialized_4.3.0.txt
License-File: opclabs_quickopc/OpcLabs.QuickOpc/System.Collections_4.3.0.txt
License-File: opclabs_quickopc/OpcLabs.QuickOpc/System.ComponentModel.EventBasedAsync_4.3.0.txt
License-File: opclabs_quickopc/OpcLabs.QuickOpc/System.ComponentModel.Primitives_4.3.0.txt
License-File: opclabs_quickopc/OpcLabs.QuickOpc/System.ComponentModel.TypeConverter_4.3.0.txt
License-File: opclabs_quickopc/OpcLabs.QuickOpc/System.ComponentModel_4.3.0.txt
License-File: opclabs_quickopc/OpcLabs.QuickOpc/System.Console_4.3.0.txt
License-File: opclabs_quickopc/OpcLabs.QuickOpc/System.Diagnostics.Contracts_4.3.0.txt
License-File: opclabs_quickopc/OpcLabs.QuickOpc/System.Diagnostics.Debug_4.3.0.txt
License-File: opclabs_quickopc/OpcLabs.QuickOpc/System.Diagnostics.DiagnosticSource_4.3.0.txt
License-File: opclabs_quickopc/OpcLabs.QuickOpc/System.Diagnostics.Tools_4.3.0.txt
License-File: opclabs_quickopc/OpcLabs.QuickOpc/System.Diagnostics.Tracing_4.3.0.txt
License-File: opclabs_quickopc/OpcLabs.QuickOpc/System.Drawing.Primitives_4.3.0.txt
License-File: opclabs_quickopc/OpcLabs.QuickOpc/System.Dynamic.Runtime_4.3.0.txt
License-File: opclabs_quickopc/OpcLabs.QuickOpc/System.Globalization.Calendars_4.3.0.txt
License-File: opclabs_quickopc/OpcLabs.QuickOpc/System.Globalization.Extensions_4.3.0.txt
License-File: opclabs_quickopc/OpcLabs.QuickOpc/System.Globalization_4.3.0.txt
License-File: opclabs_quickopc/OpcLabs.QuickOpc/System.IO.Compression.ZipFile_4.3.0.txt
License-File: opclabs_quickopc/OpcLabs.QuickOpc/System.IO.Compression_4.3.0.txt
License-File: opclabs_quickopc/OpcLabs.QuickOpc/System.IO.FileSystem.Primitives_4.3.0.txt
License-File: opclabs_quickopc/OpcLabs.QuickOpc/System.IO.FileSystem_4.3.0.txt
License-File: opclabs_quickopc/OpcLabs.QuickOpc/System.IO_4.3.0.txt
License-File: opclabs_quickopc/OpcLabs.QuickOpc/System.Linq.Expressions_4.3.0.txt
License-File: opclabs_quickopc/OpcLabs.QuickOpc/System.Linq_4.3.0.txt
License-File: opclabs_quickopc/OpcLabs.QuickOpc/System.Memory_4.5.0.txt
License-File: opclabs_quickopc/OpcLabs.QuickOpc/System.Memory_4.5.4.txt
License-File: opclabs_quickopc/OpcLabs.QuickOpc/System.Memory_4.5.5.txt
License-File: opclabs_quickopc/OpcLabs.QuickOpc/System.Net.Http_4.3.0.txt
License-File: opclabs_quickopc/OpcLabs.QuickOpc/System.Net.Http_4.3.4.txt
License-File: opclabs_quickopc/OpcLabs.QuickOpc/System.Net.NameResolution_4.3.0.txt
License-File: opclabs_quickopc/OpcLabs.QuickOpc/System.Net.Primitives_4.3.0.txt
License-File: opclabs_quickopc/OpcLabs.QuickOpc/System.Net.Requests_4.3.0.txt
License-File: opclabs_quickopc/OpcLabs.QuickOpc/System.Net.Security_4.3.2.txt
License-File: opclabs_quickopc/OpcLabs.QuickOpc/System.Net.Sockets_4.3.0.txt
License-File: opclabs_quickopc/OpcLabs.QuickOpc/System.Net.WebHeaderCollection_4.3.0.txt
License-File: opclabs_quickopc/OpcLabs.QuickOpc/System.Net.WebSockets.Client_4.3.2.txt
License-File: opclabs_quickopc/OpcLabs.QuickOpc/System.Net.WebSockets_4.3.0.txt
License-File: opclabs_quickopc/OpcLabs.QuickOpc/System.Numerics.Vectors_4.4.0.txt
License-File: opclabs_quickopc/OpcLabs.QuickOpc/System.Numerics.Vectors_4.5.0.txt
License-File: opclabs_quickopc/OpcLabs.QuickOpc/System.ObjectModel_4.3.0.txt
License-File: opclabs_quickopc/OpcLabs.QuickOpc/System.Private.DataContractSerialization_4.3.0.txt
License-File: opclabs_quickopc/OpcLabs.QuickOpc/System.Reflection.DispatchProxy_4.5.0.txt
License-File: opclabs_quickopc/OpcLabs.QuickOpc/System.Reflection.Emit.ILGeneration_4.3.0.txt
License-File: opclabs_quickopc/OpcLabs.QuickOpc/System.Reflection.Emit.Lightweight_4.3.0.txt
License-File: opclabs_quickopc/OpcLabs.QuickOpc/System.Reflection.Emit_4.3.0.txt
License-File: opclabs_quickopc/OpcLabs.QuickOpc/System.Reflection.Extensions_4.3.0.txt
License-File: opclabs_quickopc/OpcLabs.QuickOpc/System.Reflection.Primitives_4.3.0.txt
License-File: opclabs_quickopc/OpcLabs.QuickOpc/System.Reflection.TypeExtensions_4.3.0.txt
License-File: opclabs_quickopc/OpcLabs.QuickOpc/System.Reflection_4.3.0.txt
License-File: opclabs_quickopc/OpcLabs.QuickOpc/System.Resources.ResourceManager_4.3.0.txt
License-File: opclabs_quickopc/OpcLabs.QuickOpc/System.Runtime.CompilerServices.Unsafe_4.5.0.txt
License-File: opclabs_quickopc/OpcLabs.QuickOpc/System.Runtime.CompilerServices.Unsafe_4.5.3.txt
License-File: opclabs_quickopc/OpcLabs.QuickOpc/System.Runtime.Extensions_4.3.0.txt
License-File: opclabs_quickopc/OpcLabs.QuickOpc/System.Runtime.Handles_4.3.0.txt
License-File: opclabs_quickopc/OpcLabs.QuickOpc/System.Runtime.InteropServices.RuntimeInformation_4.3.0.txt
License-File: opclabs_quickopc/OpcLabs.QuickOpc/System.Runtime.InteropServices.WindowsRuntime_4.3.0.txt
License-File: opclabs_quickopc/OpcLabs.QuickOpc/System.Runtime.InteropServices_4.3.0.txt
License-File: opclabs_quickopc/OpcLabs.QuickOpc/System.Runtime.Numerics_4.3.0.txt
License-File: opclabs_quickopc/OpcLabs.QuickOpc/System.Runtime.Serialization.Primitives_4.3.0.txt
License-File: opclabs_quickopc/OpcLabs.QuickOpc/System.Runtime.Serialization.Xml_4.3.0.txt
License-File: opclabs_quickopc/OpcLabs.QuickOpc/System.Runtime.WindowsRuntime_4.3.0.txt
License-File: opclabs_quickopc/OpcLabs.QuickOpc/System.Runtime_4.1.0.txt
License-File: opclabs_quickopc/OpcLabs.QuickOpc/System.Runtime_4.3.0.txt
License-File: opclabs_quickopc/OpcLabs.QuickOpc/System.Security.AccessControl_4.5.0.txt
License-File: opclabs_quickopc/OpcLabs.QuickOpc/System.Security.Claims_4.3.0.txt
License-File: opclabs_quickopc/OpcLabs.QuickOpc/System.Security.Cryptography.Algorithms_4.3.0.txt
License-File: opclabs_quickopc/OpcLabs.QuickOpc/System.Security.Cryptography.Algorithms_4.3.1.txt
License-File: opclabs_quickopc/OpcLabs.QuickOpc/System.Security.Cryptography.Cng_4.3.0.txt
License-File: opclabs_quickopc/OpcLabs.QuickOpc/System.Security.Cryptography.Cng_4.4.0.txt
License-File: opclabs_quickopc/OpcLabs.QuickOpc/System.Security.Cryptography.Cng_4.5.0.txt
License-File: opclabs_quickopc/OpcLabs.QuickOpc/System.Security.Cryptography.Csp_4.3.0.txt
License-File: opclabs_quickopc/OpcLabs.QuickOpc/System.Security.Cryptography.Encoding_4.3.0.txt
License-File: opclabs_quickopc/OpcLabs.QuickOpc/System.Security.Cryptography.OpenSsl_4.3.0.txt
License-File: opclabs_quickopc/OpcLabs.QuickOpc/System.Security.Cryptography.Pkcs_4.5.0.txt
License-File: opclabs_quickopc/OpcLabs.QuickOpc/System.Security.Cryptography.Primitives_4.3.0.txt
License-File: opclabs_quickopc/OpcLabs.QuickOpc/System.Security.Cryptography.X509Certificates_4.3.0.txt
License-File: opclabs_quickopc/OpcLabs.QuickOpc/System.Security.Cryptography.Xml_4.5.0.txt
License-File: opclabs_quickopc/OpcLabs.QuickOpc/System.Security.Permissions_4.5.0.txt
License-File: opclabs_quickopc/OpcLabs.QuickOpc/System.Security.Principal.Windows_4.3.0.txt
License-File: opclabs_quickopc/OpcLabs.QuickOpc/System.Security.Principal.Windows_4.5.0.txt
License-File: opclabs_quickopc/OpcLabs.QuickOpc/System.Security.Principal_4.3.0.txt
License-File: opclabs_quickopc/OpcLabs.QuickOpc/System.Text.Encoding.Extensions_4.3.0.txt
License-File: opclabs_quickopc/OpcLabs.QuickOpc/System.Text.Encoding_4.3.0.txt
License-File: opclabs_quickopc/OpcLabs.QuickOpc/System.Text.RegularExpressions_4.3.0.txt
License-File: opclabs_quickopc/OpcLabs.QuickOpc/System.Threading.Tasks.Extensions_4.3.0.txt
License-File: opclabs_quickopc/OpcLabs.QuickOpc/System.Threading.Tasks.Extensions_4.5.4.txt
License-File: opclabs_quickopc/OpcLabs.QuickOpc/System.Threading.Tasks_4.3.0.txt
License-File: opclabs_quickopc/OpcLabs.QuickOpc/System.Threading.ThreadPool_4.3.0.txt
License-File: opclabs_quickopc/OpcLabs.QuickOpc/System.Threading.Thread_4.3.0.txt
License-File: opclabs_quickopc/OpcLabs.QuickOpc/System.Threading.Timer_4.3.0.txt
License-File: opclabs_quickopc/OpcLabs.QuickOpc/System.Threading_4.3.0.txt
License-File: opclabs_quickopc/OpcLabs.QuickOpc/System.ValueTuple_4.5.0.txt
License-File: opclabs_quickopc/OpcLabs.QuickOpc/System.Xml.ReaderWriter_4.3.0.txt
License-File: opclabs_quickopc/OpcLabs.QuickOpc/System.Xml.XDocument_4.3.0.txt
License-File: opclabs_quickopc/OpcLabs.QuickOpc/System.Xml.XmlDocument_4.3.0.txt
License-File: opclabs_quickopc/OpcLabs.QuickOpc/System.Xml.XmlSerializer_4.3.0.txt
License-File: opclabs_quickopc/OpcLabs.QuickOpc/runtime.native.System.IO.Compression_4.3.0.txt
License-File: opclabs_quickopc/OpcLabs.QuickOpc/runtime.native.System.Net.Http_4.3.0.txt
License-File: opclabs_quickopc/OpcLabs.QuickOpc/runtime.native.System.Net.Security_4.3.0.txt
License-File: opclabs_quickopc/OpcLabs.QuickOpc/runtime.native.System.Security.Cryptography.Apple_4.3.0.txt
License-File: opclabs_quickopc/OpcLabs.QuickOpc/runtime.native.System.Security.Cryptography.Apple_4.3.1.txt
License-File: opclabs_quickopc/OpcLabs.QuickOpc/runtime.native.System.Security.Cryptography.OpenSsl_4.3.0.txt
License-File: opclabs_quickopc/OpcLabs.QuickOpc/runtime.native.System.Security.Cryptography.OpenSsl_4.3.2.txt
License-File: opclabs_quickopc/OpcLabs.QuickOpc/runtime.native.System_4.3.0.txt
Requires-Dist: pythonnet
Dynamic: author
Dynamic: author-email
Dynamic: description
Dynamic: description-content-type
Dynamic: home-page
Dynamic: keywords
Dynamic: license-file
Dynamic: requires-dist
Dynamic: summary
